{"gameDetails":{"round":38,"maxRounds":400,"mapWidth":16,"mapHeight":8,"roundIncomeEnergy":5,"buildingPrices":{"ENERGY":20,"DEFENSE":30,"ATTACK":30,"TESLA":100},"buildingsStats":{"ENERGY":{"health":5,"constructionTime":1,"price":20,"weaponDamage":0,"weaponSpeed":0,"weaponCooldownPeriod":0,"energyGeneratedPerTurn":3,"destroyMultiplier":1,"constructionScore":3},"DEFENSE":{"health":20,"constructionTime":3,"price":30,"weaponDamage":0,"weaponSpeed":0,"weaponCooldownPeriod":0,"energyGeneratedPerTurn":0,"destroyMultiplier":1,"constructionScore":10},"ATTACK":{"health":5,"constructionTime":1,"price":30,"weaponDamage":5,"weaponSpeed":2,"weaponCooldownPeriod":3,"energyGeneratedPerTurn":0,"destroyMultiplier":1,"constructionScore":4},"TESLA":{"health":5,"constructionTime":10,"price":100,"weaponDamage":20,"weaponSpeed":0,"weaponCooldownPeriod":10,"energyGeneratedPerTurn":0,"destroyMultiplier":10,"constructionScore":20}},"ironCurtainStats":{"activeRounds":6,"resetPeriod":30,"price":100,"constructionScore":20}},"players":[{"playerType":"A","energy":99,"health":5,"hitsTaken":19,"score":2491,"ironCurtainAvailable":true,"activeIronCurtainLifetime":-8,"isIronCurtainActive":false},{"playerType":"B","energy":99,"health":20,"hitsTaken":16,"score":2695,"ironCurtainAvailable":true,"activeIronCurtainLifetime":-8,"isIronCurtainActive":false}],"gameMap":[[{"x":0,"y":0,"buildings":[{"health":5,"constructionTimeLeft":-37,"price":20,"weaponDamage":0,"weaponSpeed":0,"weaponCooldownTimeLeft":0,"weaponCooldownPeriod":0,"destroyMultiplier":1,"constructionScore":3,"energyGeneratedPerTurn":3,"maxRange":0,"buildingType":"ENERGY","energyPerShot":0,"x":0,"y":0,"playerType":"A"}],"missiles":[],"cellOwner":"A"},{"x":1,"y":0,"buildings":[{"health":5,"constructionTimeLeft":-34,"price":20,"weaponDamage":0,"weaponSpeed":0,"weaponCooldownTimeLeft":0,"weaponCooldownPeriod":0,"destroyMultiplier":1,"constructionScore":3,"energyGeneratedPerTurn":3,"maxRange":0,"buildingType":"ENERGY","energyPerShot":0,"x":1,"y":0,"playerType":"A"}],"missiles":[],"cellOwner":"A"},{"x":2,"y":0,"buildings":[{"health":5,"constructionTimeLeft":-32,"price":20,"weaponDamage":0,"weaponSpeed":0,"weaponCooldownTimeLeft":0,"weaponCooldownPeriod":0,"destroyMultiplier":1,"constructionScore":3,"energyGeneratedPerTurn":3,"maxRange":0,"buildingType":"ENERGY","energyPerShot":0,"x":2,"y":0,"playerType":"A"}],"missiles":[],"cellOwner":"A"},{"x":3,"y":0,"buildings":[{"health":5,"constructionTimeLeft":-30,"price":20,"weaponDamage":0,"weaponSpeed":0,"weaponCooldownTimeLeft":0,"weaponCooldownPeriod":0,"destroyMultiplier":1,"constructionScore":3,"energyGeneratedPerTurn":3,"maxRange":0,"buildingType":"ENERGY","energyPerShot":0,"x":3,"y":0,"playerType":"A"}],"missiles":[],"cellOwner":"A"},{"x":4,"y":0,"buildings":[{"health":5,"constructionTimeLeft":-28,"price":20,"weaponDamage":0,"weaponSpeed":0,"weaponCooldownTimeLeft":0,"weaponCooldownPeriod":0,"destroyMultiplier":1,"constructionScore":3,"energyGeneratedPerTurn":3,"maxRange":0,"buildingType":"ENERGY","energyPerShot":0,"x":4,"y":0,"playerType":"A"}],"missiles":[],"cellOwner":"A"},{"x":5,"y":0,"buildings":[{"health":5,"constructionTimeLeft":-27,"price":20,"weaponDamage":0,"weaponSpeed":0,"weaponCooldownTimeLeft":0,"weaponCooldownPeriod":0,"destroyMultiplier":1,"constructionScore":3,"energyGeneratedPerTurn":3,"maxRange":0,"buildingType":"ENERGY","energyPerShot":0,"x":5,"y":0,"playerType":"A"}],"missiles":[],"cellOwner":"A"},{"x":6,"y":0,"buildings":[],"missiles":[],"cellOwner":"A"},{"x":7,"y":0,"buildings":[],"missiles":[],"cellOwner":"A"},{"x":8,"y":0,"buildings":[],"missiles":[],"cellOwner":"B"},{"x":9,"y":0,"buildings":[],"missiles":[],"cellOwner":"B"},{"x":10,"y":0,"buildings":[{"health":5,"constructionTimeLeft":-27,"price":20,"weaponDamage":0,"weaponSpeed":0,"weaponCooldownTimeLeft":0,"weaponCooldownPeriod":0,"destroyMultiplier":1,"constructionScore":3,"energyGeneratedPerTurn":3,"maxRange":0,"buildingType":"ENERGY","energyPerShot":0,"x":10,"y":0,"playerType":"B"}],"missiles":[],"cellOwner":"B"},{"x":11,"y":0,"buildings":[{"health":5,"constructionTimeLeft":-28,"price":20,"weaponDamage":0,"weaponSpeed":0,"weaponCooldownTimeLeft":0,"weaponCooldownPeriod":0,"destroyMultiplier":1,"constructionScore":3,"energyGeneratedPerTurn":3,"maxRange":0,"buildingType":"ENERGY","energyPerShot":0,"x":11,"y":0,"playerType":"B"}],"missiles":[],"cellOwner":"B"},{"x":12,"y":0,"buildings":[{"health":5,"constructionTimeLeft":-30,"price":20,"weaponDamage":0,"weaponSpeed":0,"weaponCooldownTimeLeft":0,"weaponCooldownPeriod":0,"destroyMultiplier":1,"constructionScore":3,"energyGeneratedPerTurn":3,"maxRange":0,"buildingType":"ENERGY","energyPerShot":0,"x":12,"y":0,"playerType":"B"}],"missiles":[],"cellOwner":"B"},{"x":13,"y":0,"buildings":[{"health":5,"constructionTimeLeft":-32,"price":20,"weaponDamage":0,"weaponSpeed":0,"weaponCooldownTimeLeft":0,"weaponCooldownPeriod":0,"destroyMultiplier":1,"constructionScore":3,"energyGeneratedPerTurn":3,"maxRange":0,"buildingType":"ENERGY","energyPerShot":0,"x":13,"y":0,"playerType":"B"}],"missiles":[],"cellOwner":"B"},{"x":14,"y":0,"buildings":[{"health":5,"constructionTimeLeft":-34,"price":20,"weaponDamage":0,"weaponSpeed":0,"weaponCooldownTimeLeft":0,"weaponCooldownPeriod":0,"destroyMultiplier":1,"constructionScore":3,"energyGeneratedPerTurn":3,"maxRange":0,"buildingType":"ENERGY","energyPerShot":0,"x":14,"y":0,"playerType":"B"}],"missiles":[],"cellOwner":"B"},{"x":15,"y":0,"buildings":[{"health":5,"constructionTimeLeft":-37,"price":20,"weaponDamage":0,"weaponSpeed":0,"weaponCooldownTimeLeft":0,"weaponCooldownPeriod":0,"destroyMultiplier":1,"constructionScore":3,"energyGeneratedPerTurn":3,"maxRange":0,"buildingType":"ENERGY","energyPerShot":0,"x":15,"y":0,"playerType":"B"}],"missiles":[],"cellOwner":"B"}],[{"x":0,"y":1,"buildings":[{"health":5,"constructionTimeLeft":-26,"price":20,"weaponDamage":0,"weaponSpeed":0,"weaponCooldownTimeLeft":0,"weaponCooldownPeriod":0,"destroyMultiplier":1,"constructionScore":3,"energyGeneratedPerTurn":3,"maxRange":0,"buildingType":"ENERGY","energyPerShot":0,"x":0,"y":1,"playerType":"A"}],"missiles":[],"cellOwner":"A"},{"x":1,"y":1,"buildings":[{"health":5,"constructionTimeLeft":-25,"price":20,"weaponDamage":0,"weaponSpeed":0,"weaponCooldownTimeLeft":0,"weaponCooldownPeriod":0,"destroyMultiplier":1,"constructionScore":3,"energyGeneratedPerTurn":3,"maxRange":0,"buildingType":"ENERGY","energyPerShot":0,"x":1,"y":1,"playerType":"A"}],"missiles":[],"cellOwner":"A"},{"x":2,"y":1,"buildings":[{"health":5,"constructionTimeLeft":-24,"price":20,"weaponDamage":0,"weaponSpeed":0,"weaponCooldownTimeLeft":0,"weaponCooldownPeriod":0,"destroyMultiplier":1,"constructionScore":3,"energyGeneratedPerTurn":3,"maxRange":0,"buildingType":"ENERGY","energyPerShot":0,"x":2,"y":1,"playerType":"A"}],"missiles":[],"cellOwner":"A"},{"x":3,"y":1,"buildings":[],"missiles":[],"cellOwner":"A"},{"x":4,"y":1,"buildings":[],"missiles":[],"cellOwner":"A"},{"x":5,"y":1,"buildings":[],"missiles":[],"cellOwner":"A"},{"x":6,"y":1,"buildings":[],"missiles":[],"cellOwner":"A"},{"x":7,"y":1,"buildings":[],"missiles":[],"cellOwner":"A"},{"x":8,"y":1,"buildings":[],"missiles":[],"cellOwner":"B"},{"x":9,"y":1,"buildings":[],"missiles":[],"cellOwner":"B"},{"x":10,"y":1,"buildings":[],"missiles":[],"cellOwner":"B"},{"x":11,"y":1,"buildings":[],"missiles":[],"cellOwner":"B"},{"x":12,"y":1,"buildings":[],"missiles":[],"cellOwner":"B"},{"x":13,"y":1,"buildings":[{"health":5,"constructionTimeLeft":-24,"price":20,"weaponDamage":0,"weaponSpeed":0,"weaponCooldownTimeLeft":0,"weaponCooldownPeriod":0,"destroyMultiplier":1,"constructionScore":3,"energyGeneratedPerTurn":3,"maxRange":0,"buildingType":"ENERGY","energyPerShot":0,"x":13,"y":1,"playerType":"B"}],"missiles":[],"cellOwner":"B"},{"x":14,"y":1,"buildings":[{"health":5,"constructionTimeLeft":-25,"price":20,"weaponDamage":0,"weaponSpeed":0,"weaponCooldownTimeLeft":0,"weaponCooldownPeriod":0,"destroyMultiplier":1,"constructionScore":3,"energyGeneratedPerTurn":3,"maxRange":0,"buildingType":"ENERGY","energyPerShot":0,"x":14,"y":1,"playerType":"B"}],"missiles":[],"cellOwner":"B"},{"x":15,"y":1,"buildings":[{"health":5,"constructionTimeLeft":-26,"price":20,"weaponDamage":0,"weaponSpeed":0,"weaponCooldownTimeLeft":0,"weaponCooldownPeriod":0,"destroyMultiplier":1,"constructionScore":3,"energyGeneratedPerTurn":3,"maxRange":0,"buildingType":"ENERGY","energyPerShot":0,"x":15,"y":1,"playerType":"B"}],"missiles":[],"cellOwner":"B"}],[{"x":0,"y":2,"buildings":[{"health":5,"constructionTimeLeft":-23,"price":30,"weaponDamage":5,"weaponSpeed":2,"weaponCooldownTimeLeft":1,"weaponCooldownPeriod":3,"destroyMultiplier":1,"constructionScore":4,"energyGeneratedPerTurn":0,"maxRange":0,"buildingType":"ATTACK","energyPerShot":0,"x":0,"y":2,"playerType":"A"}],"missiles":[],"cellOwner":"A"},{"x":1,"y":2,"buildings":[{"health":5,"constructionTimeLeft":-21,"price":30,"weaponDamage":5,"weaponSpeed":2,"weaponCooldownTimeLeft":3,"weaponCooldownPeriod":3,"destroyMultiplier":1,"constructionScore":4,"energyGeneratedPerTurn":0,"maxRange":0,"buildingType":"ATTACK","energyPerShot":0,"x":1,"y":2,"playerType":"A"}],"missiles":[],"cellOwner":"A"},{"x":2,"y":2,"buildings":[{"health":5,"constructionTimeLeft":-20,"price":30,"weaponDamage":5,"weaponSpeed":2,"weaponCooldownTimeLeft":0,"weaponCooldownPeriod":3,"destroyMultiplier":1,"constructionScore":4,"energyGeneratedPerTurn":0,"maxRange":0,"buildingType":"ATTACK","energyPerShot":0,"x":2,"y":2,"playerType":"A"}],"missiles":[],"cellOwner":"A"},{"x":3,"y":2,"buildings":[{"health":5,"constructionTimeLeft":-19,"price":30,"weaponDamage":5,"weaponSpeed":2,"weaponCooldownTimeLeft":1,"weaponCooldownPeriod":3,"destroyMultiplier":1,"constructionScore":4,"energyGeneratedPerTurn":0,"maxRange":0,"buildingType":"ATTACK","energyPerShot":0,"x":3,"y":2,"playerType":"A"}],"missiles":[{"damage":5,"speed":2,"id":"97829155-88a9-42f2-bba5-18554babc6d7","x":3,"y":2,"playerType":"A"}],"cellOwner":"A"},{"x":4,"y":2,"buildings":[{"health":5,"constructionTimeLeft":-18,"price":30,"weaponDamage":5,"weaponSpeed":2,"weaponCooldownTimeLeft":2,"weaponCooldownPeriod":3,"destroyMultiplier":1,"constructionScore":4,"energyGeneratedPerTurn":0,"maxRange":0,"buildingType":"ATTACK","energyPerShot":0,"x":4,"y":2,"playerType":"A"}],"missiles":[],"cellOwner":"A"},{"x":5,"y":2,"buildings":[{"health":5,"constructionTimeLeft":-17,"price":30,"weaponDamage":5,"weaponSpeed":2,"weaponCooldownTimeLeft":3,"weaponCooldownPeriod":3,"destroyMultiplier":1,"constructionScore":4,"energyGeneratedPerTurn":0,"maxRange":0,"buildingType":"ATTACK","energyPerShot":0,"x":5,"y":2,"playerType":"A"}],"missiles":[],"cellOwner":"A"},{"x":6,"y":2,"buildings":[],"missiles":[{"damage":5,"speed":2,"id":"7217cea8-a7c6-449b-af55-de5e02c8bf96","x":6,"y":2,"playerType":"A"}],"cellOwner":"A"},{"x":7,"y":2,"buildings":[],"missiles":[{"damage":5,"speed":2,"id":"44fdbcf3-3ce4-493a-80da-87862795a977","x":7,"y":2,"playerType":"A"}],"cellOwner":"A"},{"x":8,"y":2,"buildings":[],"missiles":[],"cellOwner":"B"},{"x":9,"y":2,"buildings":[],"missiles":[],"cellOwner":"B"},{"x":10,"y":2,"buildings":[],"missiles":[],"cellOwner":"B"},{"x":11,"y":2,"buildings":[],"missiles":[],"cellOwner":"B"},{"x":12,"y":2,"buildings":[],"missiles":[],"cellOwner":"B"},{"x":13,"y":2,"buildings":[],"missiles":[],"cellOwner":"B"},{"x":14,"y":2,"buildings":[],"missiles":[{"damage":5,"speed":2,"id":"8b781299-7520-4576-a28f-301b0e5b3c08","x":14,"y":2,"playerType":"A"}],"cellOwner":"B"},{"x":15,"y":2,"buildings":[],"missiles":[{"damage":5,"speed":2,"id":"822cf576-b817-4c34-a918-8c59dc181b64","x":15,"y":2,"playerType":"A"}],"cellOwner":"B"}],[{"x":0,"y":3,"buildings":[{"health":5,"constructionTimeLeft":-16,"price":30,"weaponDamage":5,"weaponSpeed":2,"weaponCooldownTimeLeft":0,"weaponCooldownPeriod":3,"destroyMultiplier":1,"constructionScore":4,"energyGeneratedPerTurn":0,"maxRange":0,"buildingType":"ATTACK","energyPerShot":0,"x":0,"y":3,"playerType":"A"}],"missiles":[],"cellOwner":"A"},{"x":1,"y":3,"buildings":[{"health":5,"constructionTimeLeft":-14,"price":30,"weaponDamage":5,"weaponSpeed":2,"weaponCooldownTimeLeft":2,"weaponCooldownPeriod":3,"destroyMultiplier":1,"constructionScore":4,"energyGeneratedPerTurn":0,"maxRange":0,"buildingType":"ATTACK","energyPerShot":0,"x":1,"y":3,"playerType":"A"}],"missiles":[],"cellOwner":"A"},{"x":2,"y":3,"buildings":[{"health":5,"constructionTimeLeft":-13,"price":30,"weaponDamage":5,"weaponSpeed":2,"weaponCooldownTimeLeft":3,"weaponCooldownPeriod":3,"destroyMultiplier":1,"constructionScore":4,"energyGeneratedPerTurn":0,"maxRange":0,"buildingType":"ATTACK","energyPerShot":0,"x":2,"y":3,"playerType":"A"}],"missiles":[],"cellOwner":"A"},{"x":3,"y":3,"buildings":[{"health":5,"constructionTimeLeft":-11,"price":30,"weaponDamage":5,"weaponSpeed":2,"weaponCooldownTimeLeft":1,"weaponCooldownPeriod":3,"destroyMultiplier":1,"constructionScore":4,"energyGeneratedPerTurn":0,"maxRange":0,"buildingType":"ATTACK","energyPerShot":0,"x":3,"y":3,"playerType":"A"}],"missiles":[],"cellOwner":"A"},{"x":4,"y":3,"buildings":[{"health":5,"constructionTimeLeft":-9,"price":30,"weaponDamage":5,"weaponSpeed":2,"weaponCooldownTimeLeft":3,"weaponCooldownPeriod":3,"destroyMultiplier":1,"constructionScore":4,"energyGeneratedPerTurn":0,"maxRange":0,"buildingType":"ATTACK","energyPerShot":0,"x":4,"y":3,"playerType":"A"}],"missiles":[{"damage":5,"speed":2,"id":"f5ec656a-3846-4c6f-a65a-78cea5d211a7","x":4,"y":3,"playerType":"A"}],"cellOwner":"A"},{"x":5,"y":3,"buildings":[{"health":5,"constructionTimeLeft":-8,"price":30,"weaponDamage":5,"weaponSpeed":2,"weaponCooldownTimeLeft":0,"weaponCooldownPeriod":3,"destroyMultiplier":1,"constructionScore":4,"energyGeneratedPerTurn":0,"maxRange":0,"buildingType":"ATTACK","energyPerShot":0,"x":5,"y":3,"playerType":"A"}],"missiles":[{"damage":5,"speed":2,"id":"54876814-253b-4571-8077-c3cd81a56566","x":5,"y":3,"playerType":"A"}],"cellOwner":"A"},{"x":6,"y":3,"buildings":[],"missiles":[{"damage":5,"speed":2,"id":"e3094549-69c3-490f-9b9e-995c96d46cc5","x":6,"y":3,"playerType":"A"}],"cellOwner":"A"},{"x":7,"y":3,"buildings":[],"missiles":[],"cellOwner":"A"},{"x":8,"y":3,"buildings":[{"health":20,"constructionTimeLeft":1,"price":30,"weaponDamage":0,"weaponSpeed":0,"weaponCooldownTimeLeft":0,"weaponCooldownPeriod":0,"destroyMultiplier":1,"constructionScore":10,"energyGeneratedPerTurn":0,"maxRange":0,"buildingType":"DEFENSE","energyPerShot":0,"x":8,"y":3,"playerType":"B"}],"missiles":[{"damage":5,"speed":2,"id":"2f33c4db-aaa1-49a8-96f9-45f1d5ddcae1","x":8,"y":3,"playerType":"A"}],"cellOwner":"B"},{"x":9,"y":3,"buildings":[],"missiles":[{"damage":5,"speed":2,"id":"3033270b-50de-4e6f-89d5-7d1d15777cb1","x":9,"y":3,"playerType":"A"}],"cellOwner":"B"},{"x":10,"y":3,"buildings":[],"missiles":[],"cellOwner":"B"},{"x":11,"y":3,"buildings":[],"missiles":[],"cellOwner":"B"},{"x":12,"y":3,"buildings":[],"missiles":[{"damage":5,"speed":2,"id":"109adb9e-e284-46be-97a4-e92460588b14","x":12,"y":3,"playerType":"A"}],"cellOwner":"B"},{"x":13,"y":3,"buildings":[],"missiles":[{"damage":5,"speed":2,"id":"d01a1240-feab-44ae-b12a-e5cbd16f257d","x":13,"y":3,"playerType":"A"}],"cellOwner":"B"},{"x":14,"y":3,"buildings":[],"missiles":[],"cellOwner":"B"},{"x":15,"y":3,"buildings":[],"missiles":[],"cellOwner":"B"}],[{"x":0,"y":4,"buildings":[{"health":5,"constructionTimeLeft":-7,"price":30,"weaponDamage":5,"weaponSpeed":2,"weaponCooldownTimeLeft":1,"weaponCooldownPeriod":3,"destroyMultiplier":1,"constructionScore":4,"energyGeneratedPerTurn":0,"maxRange":0,"buildingType":"ATTACK","energyPerShot":0,"x":0,"y":4,"playerType":"A"}],"missiles":[],"cellOwner":"A"},{"x":1,"y":4,"buildings":[{"health":5,"constructionTimeLeft":-6,"price":30,"weaponDamage":5,"weaponSpeed":2,"weaponCooldownTimeLeft":2,"weaponCooldownPeriod":3,"destroyMultiplier":1,"constructionScore":4,"energyGeneratedPerTurn":0,"maxRange":0,"buildingType":"ATTACK","energyPerShot":0,"x":1,"y":4,"playerType":"A"}],"missiles":[],"cellOwner":"A"},{"x":2,"y":4,"buildings":[{"health":5,"constructionTimeLeft":-3,"price":30,"weaponDamage":5,"weaponSpeed":2,"weaponCooldownTimeLeft":1,"weaponCooldownPeriod":3,"destroyMultiplier":1,"constructionScore":4,"energyGeneratedPerTurn":0,"maxRange":0,"buildingType":"ATTACK","energyPerShot":0,"x":2,"y":4,"playerType":"A"}],"missiles":[],"cellOwner":"A"},{"x":3,"y":4,"buildings":[{"health":5,"constructionTimeLeft":-2,"price":30,"weaponDamage":5,"weaponSpeed":2,"weaponCooldownTimeLeft":2,"weaponCooldownPeriod":3,"destroyMultiplier":1,"constructionScore":4,"energyGeneratedPerTurn":0,"maxRange":0,"buildingType":"ATTACK","energyPerShot":0,"x":3,"y":4,"playerType":"A"}],"missiles":[],"cellOwner":"A"},{"x":4,"y":4,"buildings":[],"missiles":[],"cellOwner":"A"},{"x":5,"y":4,"buildings":[],"missiles":[{"damage":5,"speed":2,"id":"efb82d72-5d51-473f-ad1c-bb945b95a7d8","x":5,"y":4,"playerType":"A"}],"cellOwner":"A"},{"x":6,"y":4,"buildings":[],"missiles":[{"damage":5,"speed":2,"id":"95745c14-d756-46c3-ae00-fa1f48c4b0da","x":6,"y":4,"playerType":"A"}],"cellOwner":"A"},{"x":7,"y":4,"buildings":[],"missiles":[{"damage":5,"speed":2,"id":"1dafe717-a1d4-48f5-b998-5f2974e50773","x":7,"y":4,"playerType":"A"}],"cellOwner":"A"},{"x":8,"y":4,"buildings":[{"health":5,"constructionTimeLeft":-4,"price":30,"weaponDamage":0,"weaponSpeed":0,"weaponCooldownTimeLeft":0,"weaponCooldownPeriod":0,"destroyMultiplier":1,"constructionScore":10,"energyGeneratedPerTurn":0,"maxRange":0,"buildingType":"DEFENSE","energyPerShot":0,"x":8,"y":4,"playerType":"B"}],"missiles":[],"cellOwner":"B"},{"x":9,"y":4,"buildings":[],"missiles":[],"cellOwner":"B"},{"x":10,"y":4,"buildings":[],"missiles":[],"cellOwner":"B"},{"x":11,"y":4,"buildings":[],"missiles":[],"cellOwner":"B"},{"x":12,"y":4,"buildings":[],"missiles":[],"cellOwner":"B"},{"x":13,"y":4,"buildings":[],"missiles":[],"cellOwner":"B"},{"x":14,"y":4,"buildings":[],"missiles":[],"cellOwner":"B"},{"x":15,"y":4,"buildings":[],"missiles":[],"cellOwner":"B"}],[{"x":0,"y":5,"buildings":[],"missiles":[],"cellOwner":"A"},{"x":1,"y":5,"buildings":[],"missiles":[],"cellOwner":"A"},{"x":2,"y":5,"buildings":[],"missiles":[],"cellOwner":"A"},{"x":3,"y":5,"buildings":[],"missiles":[],"cellOwner":"A"},{"x":4,"y":5,"buildings":[],"missiles":[],"cellOwner":"A"},{"x":5,"y":5,"buildings":[],"missiles":[{"damage":5,"speed":2,"id":"95e6eb2b-c72b-4fc2-8e71-646c6ae2c6d5","x":5,"y":5,"playerType":"B"}],"cellOwner":"A"},{"x":6,"y":5,"buildings":[],"missiles":[],"cellOwner":"A"},{"x":7,"y":5,"buildings":[{"health":20,"constructionTimeLeft":1,"price":30,"weaponDamage":0,"weaponSpeed":0,"weaponCooldownTimeLeft":0,"weaponCooldownPeriod":0,"destroyMultiplier":1,"constructionScore":10,"energyGeneratedPerTurn":0,"maxRange":0,"buildingType":"DEFENSE","energyPerShot":0,"x":7,"y":5,"playerType":"A"}],"missiles":[],"cellOwner":"A"},{"x":8,"y":5,"buildings":[],"missiles":[],"cellOwner":"B"},{"x":9,"y":5,"buildings":[{"health":5,"constructionTimeLeft":-2,"price":30,"weaponDamage":5,"weaponSpeed":2,"weaponCooldownTimeLeft":2,"weaponCooldownPeriod":3,"destroyMultiplier":1,"constructionScore":4,"energyGeneratedPerTurn":0,"maxRange":0,"buildingType":"ATTACK","energyPerShot":0,"x":9,"y":5,"playerType":"B"}],"missiles":[],"cellOwner":"B"},{"x":10,"y":5,"buildings":[{"health":5,"constructionTimeLeft":0,"price":30,"weaponDamage":5,"weaponSpeed":2,"weaponCooldownTimeLeft":0,"weaponCooldownPeriod":3,"destroyMultiplier":1,"constructionScore":4,"energyGeneratedPerTurn":0,"maxRange":0,"buildingType":"ATTACK","energyPerShot":0,"x":10,"y":5,"playerType":"B"}],"missiles":[],"cellOwner":"B"},{"x":11,"y":5,"buildings":[],"missiles":[],"cellOwner":"B"},{"x":12,"y":5,"buildings":[],"missiles":[],"cellOwner":"B"},{"x":13,"y":5,"buildings":[],"missiles":[],"cellOwner":"B"},{"x":14,"y":5,"buildings":[],"missiles":[],"cellOwner":"B"},{"x":15,"y":5,"buildings":[],"missiles":[],"cellOwner":"B"}],[{"x":0,"y":6,"buildings":[],"missiles":[],"cellOwner":"A"},{"x":1,"y":6,"buildings":[],"missiles":[],"cellOwner":"A"},{"x":2,"y":6,"buildings":[],"missiles":[],"cellOwner":"A"},{"x":3,"y":6,"buildings":[],"missiles":[],"cellOwner":"A"},{"x":4,"y":6,"buildings":[],"missiles":[],"cellOwner":"A"},{"x":5,"y":6,"buildings":[],"missiles":[{"damage":5,"speed":2,"id":"3a536571-2e63-4f35-8782-9f0c509c4c78","x":5,"y":6,"playerType":"B"}],"cellOwner":"A"},{"x":6,"y":6,"buildings":[],"missiles":[],"cellOwner":"A"},{"x":7,"y":6,"buildings":[{"health":20,"constructionTimeLeft":2,"price":30,"weaponDamage":0,"weaponSpeed":0,"weaponCooldownTimeLeft":0,"weaponCooldownPeriod":0,"destroyMultiplier":1,"constructionScore":10,"energyGeneratedPerTurn":0,"maxRange":0,"buildingType":"DEFENSE","energyPerShot":0,"x":7,"y":6,"playerType":"A"}],"missiles":[{"damage":5,"speed":2,"id":"beb66871-bbf8-480c-afcd-da105bf26df6","x":7,"y":6,"playerType":"B"}],"cellOwner":"A"},{"x":8,"y":6,"buildings":[],"missiles":[],"cellOwner":"B"},{"x":9,"y":6,"buildings":[{"health":5,"constructionTimeLeft":-13,"price":30,"weaponDamage":5,"weaponSpeed":2,"weaponCooldownTimeLeft":3,"weaponCooldownPeriod":3,"destroyMultiplier":1,"constructionScore":4,"energyGeneratedPerTurn":0,"maxRange":0,"buildingType":"ATTACK","energyPerShot":0,"x":9,"y":6,"playerType":"B"}],"missiles":[{"damage":5,"speed":2,"id":"c45b6e51-e850-4571-8bdf-e1d858bb2b3d","x":9,"y":6,"playerType":"B"}],"cellOwner":"B"},{"x":10,"y":6,"buildings":[{"health":5,"constructionTimeLeft":-12,"price":30,"weaponDamage":5,"weaponSpeed":2,"weaponCooldownTimeLeft":0,"weaponCooldownPeriod":3,"destroyMultiplier":1,"constructionScore":4,"energyGeneratedPerTurn":0,"maxRange":0,"buildingType":"ATTACK","energyPerShot":0,"x":10,"y":6,"playerType":"B"}],"missiles":[{"damage":5,"speed":2,"id":"8c9fa4a1-ea35-4bdf-a1c3-c7220f437f52","x":10,"y":6,"playerType":"B"}],"cellOwner":"B"},{"x":11,"y":6,"buildings":[{"health":5,"constructionTimeLeft":-11,"price":30,"weaponDamage":5,"weaponSpeed":2,"weaponCooldownTimeLeft":1,"weaponCooldownPeriod":3,"destroyMultiplier":1,"constructionScore":4,"energyGeneratedPerTurn":0,"maxRange":0,"buildingType":"ATTACK","energyPerShot":0,"x":11,"y":6,"playerType":"B"}],"missiles":[],"cellOwner":"B"},{"x":12,"y":6,"buildings":[{"health":5,"constructionTimeLeft":-9,"price":30,"weaponDamage":5,"weaponSpeed":2,"weaponCooldownTimeLeft":3,"weaponCooldownPeriod":3,"destroyMultiplier":1,"constructionScore":4,"energyGeneratedPerTurn":0,"maxRange":0,"buildingType":"ATTACK","energyPerShot":0,"x":12,"y":6,"playerType":"B"}],"missiles":[{"damage":5,"speed":2,"id":"be3e5fa4-1e1e-40be-9d50-869b03c9a352","x":12,"y":6,"playerType":"B"}],"cellOwner":"B"},{"x":13,"y":6,"buildings":[{"health":5,"constructionTimeLeft":-8,"price":30,"weaponDamage":5,"weaponSpeed":2,"weaponCooldownTimeLeft":0,"weaponCooldownPeriod":3,"destroyMultiplier":1,"constructionScore":4,"energyGeneratedPerTurn":0,"maxRange":0,"buildingType":"ATTACK","energyPerShot":0,"x":13,"y":6,"playerType":"B"}],"missiles":[],"cellOwner":"B"},{"x":14,"y":6,"buildings":[{"health":5,"constructionTimeLeft":-5,"price":30,"weaponDamage":5,"weaponSpeed":2,"weaponCooldownTimeLeft":3,"weaponCooldownPeriod":3,"destroyMultiplier":1,"constructionScore":4,"energyGeneratedPerTurn":0,"maxRange":0,"buildingType":"ATTACK","energyPerShot":0,"x":14,"y":6,"playerType":"B"}],"missiles":[],"cellOwner":"B"},{"x":15,"y":6,"buildings":[{"health":5,"constructionTimeLeft":-3,"price":30,"weaponDamage":5,"weaponSpeed":2,"weaponCooldownTimeLeft":1,"weaponCooldownPeriod":3,"destroyMultiplier":1,"constructionScore":4,"energyGeneratedPerTurn":0,"maxRange":0,"buildingType":"ATTACK","energyPerShot":0,"x":15,"y":6,"playerType":"B"}],"missiles":[],"cellOwner":"B"}],[{"x":0,"y":7,"buildings":[],"missiles":[{"damage":5,"speed":2,"id":"3cfe09c1-4ede-4f5c-aa7e-bb4f001ffaf6","x":0,"y":7,"playerType":"B"}],"cellOwner":"A"},{"x":1,"y":7,"buildings":[],"missiles":[{"damage":5,"speed":2,"id":"81167363-c1ec-4be2-b503-e59806c5befe","x":1,"y":7,"playerType":"B"}],"cellOwner":"A"},{"x":2,"y":7,"buildings":[],"missiles":[],"cellOwner":"A"},{"x":3,"y":7,"buildings":[],"missiles":[{"damage":5,"speed":2,"id":"76def788-504f-40d1-960a-bcd7bcdcd24d","x":3,"y":7,"playerType":"B"},{"damage":5,"speed":2,"id":"fbe0d0f1-d376-4fa0-99b7-28e9c006e302","x":3,"y":7,"playerType":"B"}],"cellOwner":"A"},{"x":4,"y":7,"buildings":[],"missiles":[],"cellOwner":"A"},{"x":5,"y":7,"buildings":[],"missiles":[],"cellOwner":"A"},{"x":6,"y":7,"buildings":[],"missiles":[],"cellOwner":"A"},{"x":7,"y":7,"buildings":[{"health":5,"constructionTimeLeft":-2,"price":30,"weaponDamage":0,"weaponSpeed":0,"weaponCooldownTimeLeft":0,"weaponCooldownPeriod":0,"destroyMultiplier":1,"constructionScore":10,"energyGeneratedPerTurn":0,"maxRange":0,"buildingType":"DEFENSE","energyPerShot":0,"x":7,"y":7,"playerType":"A"}],"missiles":[],"cellOwner":"A"},{"x":8,"y":7,"buildings":[],"missiles":[{"damage":5,"speed":2,"id":"c10997b8-1dda-44cf-b6c7-7d730dc53334","x":8,"y":7,"playerType":"B"}],"cellOwner":"B"},{"x":9,"y":7,"buildings":[{"health":5,"constructionTimeLeft":-23,"price":30,"weaponDamage":5,"weaponSpeed":2,"weaponCooldownTimeLeft":1,"weaponCooldownPeriod":3,"destroyMultiplier":1,"constructionScore":4,"energyGeneratedPerTurn":0,"maxRange":0,"buildingType":"ATTACK","energyPerShot":0,"x":9,"y":7,"playerType":"B"}],"missiles":[{"damage":5,"speed":2,"id":"3f469a39-668e-486d-bd25-d8106a02e5f9","x":9,"y":7,"playerType":"B"}],"cellOwner":"B"},{"x":10,"y":7,"buildings":[{"health":5,"constructionTimeLeft":-21,"price":30,"weaponDamage":5,"weaponSpeed":2,"weaponCooldownTimeLeft":3,"weaponCooldownPeriod":3,"destroyMultiplier":1,"constructionScore":4,"energyGeneratedPerTurn":0,"maxRange":0,"buildingType":"ATTACK","energyPerShot":0,"x":10,"y":7,"playerType":"B"}],"missiles":[],"cellOwner":"B"},{"x":11,"y":7,"buildings":[{"health":5,"constructionTimeLeft":-20,"price":30,"weaponDamage":5,"weaponSpeed":2,"weaponCooldownTimeLeft":0,"weaponCooldownPeriod":3,"destroyMultiplier":1,"constructionScore":4,"energyGeneratedPerTurn":0,"maxRange":0,"buildingType":"ATTACK","energyPerShot":0,"x":11,"y":7,"playerType":"B"}],"missiles":[],"cellOwner":"B"},{"x":12,"y":7,"buildings":[{"health":5,"constructionTimeLeft":-19,"price":30,"weaponDamage":5,"weaponSpeed":2,"weaponCooldownTimeLeft":1,"weaponCooldownPeriod":3,"destroyMultiplier":1,"constructionScore":4,"energyGeneratedPerTurn":0,"maxRange":0,"buildingType":"ATTACK","energyPerShot":0,"x":12,"y":7,"playerType":"B"}],"missiles":[{"damage":5,"speed":2,"id":"a1e3d6a7-361c-463f-bd32-30d7a3721fe8","x":12,"y":7,"playerType":"B"}],"cellOwner":"B"},{"x":13,"y":7,"buildings":[{"health":5,"constructionTimeLeft":-18,"price":30,"weaponDamage":5,"weaponSpeed":2,"weaponCooldownTimeLeft":2,"weaponCooldownPeriod":3,"destroyMultiplier":1,"constructionScore":4,"energyGeneratedPerTurn":0,"maxRange":0,"buildingType":"ATTACK","energyPerShot":0,"x":13,"y":7,"playerType":"B"}],"missiles":[],"cellOwner":"B"},{"x":14,"y":7,"buildings":[{"health":5,"constructionTimeLeft":-17,"price":30,"weaponDamage":5,"weaponSpeed":2,"weaponCooldownTimeLeft":3,"weaponCooldownPeriod":3,"destroyMultiplier":1,"constructionScore":4,"energyGeneratedPerTurn":0,"maxRange":0,"buildingType":"ATTACK","energyPerShot":0,"x":14,"y":7,"playerType":"B"}],"missiles":[],"cellOwner":"B"},{"x":15,"y":7,"buildings":[{"health":5,"constructionTimeLeft":-16,"price":30,"weaponDamage":5,"weaponSpeed":2,"weaponCooldownTimeLeft":0,"weaponCooldownPeriod":3,"destroyMultiplier":1,"constructionScore":4,"energyGeneratedPerTurn":0,"maxRange":0,"buildingType":"ATTACK","energyPerShot":0,"x":15,"y":7,"playerType":"B"}],"missiles":[],"cellOwner":"B"}]],"teslaHitList":[],"ironCurtainHitList":[]}